rxnn/__init__.py
rxnn-0.3.1.dist-info/LICENSE
rxnn-0.3.1.dist-info/METADATA
rxnn-0.3.1.dist-info/WHEEL
rxnn-0.3.1.dist-info/RECORD
