Metadata-Version: 2.3
Name: rxnn
Version: 0.3.1
Summary: RxNN: Reactive Neural Networks Platform (coming soon)
License: Apache-2.0
Keywords: deep-learning,ai,machine-learning
Author: Adam Filipek
Author-email: adamfilipek@rxai.dev
Requires-Python: >=3.10
Classifier: License :: OSI Approved :: Apache Software License
Classifier: Programming Language :: Python :: 3
Classifier: Programming Language :: Python :: 3.10
Classifier: Programming Language :: Python :: 3.11
Classifier: Programming Language :: Python :: 3.12
Classifier: Programming Language :: Python :: 3.13
Requires-Dist: datasets (>=3.5.0,<4.0.0)
Requires-Dist: huggingface-hub (>=0.30.0,<0.31.0)
Requires-Dist: nltk (>=3.9.1,<4.0.0)
Requires-Dist: tensorboard (>=2.19.0,<3.0.0)
Requires-Dist: tokenizers (>=0.21.0,<0.22.0)
Requires-Dist: torch (>=2.6.0,<3.0.0)
Requires-Dist: transformers (>=4.51.0,<5.0.0)
Project-URL: Homepage, https://rxai.dev/docs/rxnn
Project-URL: Repository, https://github.com/RxAI-dev/rxnn
